rocketables/test.py
rocketui-0.1.0.dist-info/licenses/LICENSE
widgets/button.py
widgets/column.py
widgets/row.py
widgets/text.py
widgets/textinput.py
rocketui-0.1.0.dist-info/METADATA
rocketui-0.1.0.dist-info/WHEEL
rocketui-0.1.0.dist-info/top_level.txt
rocketui-0.1.0.dist-info/RECORD
