Metadata-Version: 2.4
Name: RocketUI
Version: 0.1.0
Summary: A fast Qt6-based reactive UI framework for Python
Author-email: NEOAPPS <asd22.info@gmail.com>
License:                     GNU GENERAL PUBLIC LICENSE
Requires-Python: >=3.9
License-File: LICENSE
Requires-Dist: PySide6
Provides-Extra: dev
Requires-Dist: pytest; extra == "dev"
Requires-Dist: black; extra == "dev"
Requires-Dist: mypy; extra == "dev"
Dynamic: license-file
